topmodule.v
module topmodule (
    input global_clk,
    input reset,
    input enable,
    output reg [3:0]out
);
always @(posedge global_clk) begin
    out <= out+4'b0010;
end
always @(posedge reset) begin
    out<=4'b0001;
end
endmodule

tb_topmodule.v
`include "topmodule.v"
`default_nettype none

module tb_topmodule;
reg clk;
reg rst_n;
reg enable;
output wire [3:0] out;

topmodule mod
(
    .global_clk(clk),
    .reset(rst_n),
    .enable(enable),
    .out(out)
);

localparam CLK_PERIOD = 10;
always #(CLK_PERIOD/2) clk=~clk;

initial begin
    $dumpfile("tb_topmodule.vcd");
    $dumpvars(0, tb_topmodule);
end

initial begin
    #1 rst_n<=1'bx;clk<=1'bx;enable<=1'bx;
    #(CLK_PERIOD*3) rst_n<=1;
    #(CLK_PERIOD*3) rst_n<=0;clk<=0;
    repeat(5) @(posedge clk);
    rst_n<=1;
    @(posedge clk);
    repeat(100) @(posedge clk);
    $finish(2);
end

endmodule
`default_nettype wire

tb_topmodule.vcd
$date
	Fri Oct 25 18:10:57 2024
$end
$version
	Icarus Verilog
$end
$timescale
	1s
$end
$scope module tb_topmodule $end
$var wire 4 ! out [3:0] $end
$var parameter 32 " CLK_PERIOD $end
$var reg 1 # clk $end
$var reg 1 $ enable $end
$var reg 1 % rst_n $end
$scope module mod $end
$var wire 1 $ enable $end
$var wire 1 # global_clk $end
$var wire 1 % reset $end
$var reg 4 & out [3:0] $end
$upscope $end
$upscope $end
$enddefinitions $end
$comment Show the parameter values. $end
$dumpall
b1010 "
$end
#0
$dumpvars
bx &
x%
x$
x#
bx !
$end
#31
b1 !
b1 &
1%
#61
0#
0%
#65
b11 !
b11 &
1#
#70
0#
#75
b101 !
b101 &
1#
#80
0#
#85
b111 !
b111 &
1#
#90
0#
#95
b1001 !
b1001 &
1#
#100
0#
#105
b1 !
b1 &
1%
1#
#110
0#
#115
b11 !
b11 &
1#
#120
0#
#125
b101 !
b101 &
1#
#130
0#
#135
b111 !
b111 &
1#
#140
0#
#145
b1001 !
b1001 &
1#
#150
0#
#155
b1011 !
b1011 &
1#
#160
0#
#165
b1101 !
b1101 &
1#
#170
0#
#175
b1111 !
b1111 &
1#
#180
0#
#185
b1 !
b1 &
1#
#190
0#
#195
b11 !
b11 &
1#
#200
0#
#205
b101 !
b101 &
1#
#210
0#
#215
b111 !
b111 &
1#
#220
0#
#225
b1001 !
b1001 &
1#
#230
0#
#235
b1011 !
b1011 &
1#
#240
0#
#245
b1101 !
b1101 &
1#
#250
0#
#255
b1111 !
b1111 &
1#
#260
0#
#265
b1 !
b1 &
1#
#270
0#
#275
b11 !
b11 &
1#
#280
0#
#285
b101 !
b101 &
1#
#290
0#
#295
b111 !
b111 &
1#
#300
0#
#305
b1001 !
b1001 &
1#
#310
0#
#315
b1011 !
b1011 &
1#
#320
0#
#325
b1101 !
b1101 &
1#
#330
0#
#335
b1111 !
b1111 &
1#
#340
0#
#345
b1 !
b1 &
1#
#350
0#
#355
b11 !
b11 &
1#
#360
0#
#365
b101 !
b101 &
1#
#370
0#
#375
b111 !
b111 &
1#
#380
0#
#385
b1001 !
b1001 &
1#
#390
0#
#395
b1011 !
b1011 &
1#
#400
0#
#405
b1101 !
b1101 &
1#
#410
0#
#415
b1111 !
b1111 &
1#
#420
0#
#425
b1 !
b1 &
1#
#430
0#
#435
b11 !
b11 &
1#
#440
0#
#445
b101 !
b101 &
1#
#450
0#
#455
b111 !
b111 &
1#
#460
0#
#465
b1001 !
b1001 &
1#
#470
0#
#475
b1011 !
b1011 &
1#
#480
0#
#485
b1101 !
b1101 &
1#
#490
0#
#495
b1111 !
b1111 &
1#
#500
0#
#505
b1 !
b1 &
1#
#510
0#
#515
b11 !
b11 &
1#
#520
0#
#525
b101 !
b101 &
1#
#530
0#
#535
b111 !
b111 &
1#
#540
0#
#545
b1001 !
b1001 &
1#
#550
0#
#555
b1011 !
b1011 &
1#
#560
0#
#565
b1101 !
b1101 &
1#
#570
0#
#575
b1111 !
b1111 &
1#
#580
0#
#585
b1 !
b1 &
1#
#590
0#
#595
b11 !
b11 &
1#
#600
0#
#605
b101 !
b101 &
1#
#610
0#
#615
b111 !
b111 &
1#
#620
0#
#625
b1001 !
b1001 &
1#
#630
0#
#635
b1011 !
b1011 &
1#
#640
0#
#645
b1101 !
b1101 &
1#
#650
0#
#655
b1111 !
b1111 &
1#
#660
0#
#665
b1 !
b1 &
1#
#670
0#
#675
b11 !
b11 &
1#
#680
0#
#685
b101 !
b101 &
1#
#690
0#
#695
b111 !
b111 &
1#
#700
0#
#705
b1001 !
b1001 &
1#
#710
0#
#715
b1011 !
b1011 &
1#
#720
0#
#725
b1101 !
b1101 &
1#
#730
0#
#735
b1111 !
b1111 &
1#
#740
0#
#745
b1 !
b1 &
1#
#750
0#
#755
b11 !
b11 &
1#
#760
0#
#765
b101 !
b101 &
1#
#770
0#
#775
b111 !
b111 &
1#
#780
0#
#785
b1001 !
b1001 &
1#
#790
0#
#795
b1011 !
b1011 &
1#
#800
0#
#805
b1101 !
b1101 &
1#
#810
0#
#815
b1111 !
b1111 &
1#
#820
0#
#825
b1 !
b1 &
1#
#830
0#
#835
b11 !
b11 &
1#
#840
0#
#845
b101 !
b101 &
1#
#850
0#
#855
b111 !
b111 &
1#
#860
0#
#865
b1001 !
b1001 &
1#
#870
0#
#875
b1011 !
b1011 &
1#
#880
0#
#885
b1101 !
b1101 &
1#
#890
0#
#895
b1111 !
b1111 &
1#
#900
0#
#905
b1 !
b1 &
1#
#910
0#
#915
b11 !
b11 &
1#
#920
0#
#925
b101 !
b101 &
1#
#930
0#
#935
b111 !
b111 &
1#
#940
0#
#945
b1001 !
b1001 &
1#
#950
0#
#955
b1011 !
b1011 &
1#
#960
0#
#965
b1101 !
b1101 &
1#
#970
0#
#975
b1111 !
b1111 &
1#
#980
0#
#985
b1 !
b1 &
1#
#990
0#
#995
b11 !
b11 &
1#
#1000
0#
#1005
b101 !
b101 &
1#
#1010
0#
#1015
b111 !
b111 &
1#
#1020
0#
#1025
b1001 !
b1001 &
1#
#1030
0#
#1035
b1011 !
b1011 &
1#
#1040
0#
#1045
b1101 !
b1101 &
1#
#1050
0#
#1055
b1111 !
b1111 &
1#
#1060
0#
#1065
b1 !
b1 &
1#
#1070
0#
#1075
b11 !
b11 &
1#
#1080
0#
#1085
b101 !
b101 &
1#
#1090
0#
#1095
b111 !
b111 &
1#
#1100
0#
#1105
b1001 !
b1001 &
1#
#1110
0#
#1115
b1011 !
b1011 &
1#
